lr_etl/__init__.py
lr_etl/Config/__init__.py
lr_etl/Libs/__init__.py
lr_etl/Libs/date.py
lr_etl/Libs/db/sql_aux.py
lr_etl/Libs/db/sql_uteis.py
lr_etl/Libs/file.py
lr_etl/Libs/log.py
lr_etl/Models/__init__.py
lr_etl/Models/adapter.py
lr_etl/Models/db/__init__.py
lr_etl/Models/db/db_handler.py
lr_etl/Models/entities/__init__.py
lr_etl/Models/entities/db_config.py
lr_etl/Models/entities/general_config.py
lr_etl/Models/entities/log_model.py
lr_etl/Models/lr.py
lr_etl/Steps/__init__.py
lr_etl/Steps/process.py
lr_etl/use_cases/__init__.py
lr_etl/use_cases/extract_data.py
lr_etl/use_cases/parse_data.py
lr_etl/use_cases/rebuild.py
lr_etl/use_cases/repository.py
lr_etl-0.0.7.dist-info/WHEEL
lr_etl-0.0.7.dist-info/METADATA
lr_etl-0.0.7.dist-info/RECORD
