Metadata-Version: 2.1
Name: lr-etl
Version: 0.0.7
Summary: 
Author: FernandoEmerson
Requires-Python: >=3.10,<4.0
Classifier: Programming Language :: Python :: 3
Classifier: Programming Language :: Python :: 3.10
Classifier: Programming Language :: Python :: 3.11
Requires-Dist: alive-progress (>=2.4.1,<3.0.0)
Requires-Dist: pandas (>=1.5.1,<2.0.0)
Requires-Dist: paramiko (>=2.12.0,<3.0.0)
Requires-Dist: psutil (>=5.9.4,<6.0.0)
Requires-Dist: pyodbc (>=4.0.35,<5.0.0)
Requires-Dist: requests (>=2.28.1,<3.0.0)
Requires-Dist: sqlalchemy (>=1.4.44,<2.0.0)
Requires-Dist: sqlalchemy-utils (>=0.38.3,<0.39.0)
